dcyd/__init__.py
dcyd/config.py
dcyd/dcyd.py
dcyd/gcl_patch.py
dcyd/gcp.py
dcyd/utils.py
dcyd/static/dcyd-ascii-art.txt
dcyd-1.3.0.dist-info/METADATA
dcyd-1.3.0.dist-info/WHEEL
dcyd-1.3.0.dist-info/entry_points.txt
dcyd-1.3.0.dist-info/top_level.txt
dcyd-1.3.0.dist-info/RECORD
