Metadata-Version: 2.1
Name: dcyd
Version: 1.3.0
Summary: dcyd model performance monitoring client
Home-page: https://github.com/dcyd-inc/dcyd-mpm-client-python
Author: dcyd, inc.
Author-email: info@dcyd.io
License: UNKNOWN
Platform: UNKNOWN
Classifier: Programming Language :: Python :: 3
Classifier: Operating System :: OS Independent
Requires-Python: >=3.5
Requires-Dist: google-cloud-logging (==2.2.0)
Requires-Dist: requests
